detextify/__init__.py
detextify/annotation_parser.py
detextify/config/ls_object_detection_config.xml
detextify/detextifier.py
detextify/inpainter.py
detextify/text_detector.py
detextify/utils.py
detextify-0.1.9.dist-info/LICENSE
detextify-0.1.9.dist-info/METADATA
detextify-0.1.9.dist-info/WHEEL
detextify-0.1.9.dist-info/RECORD
